{
	"sections": [
		{
			"fu_type": "o_breadcrumbs",
			"items": [
				{
					"text": "Home",
					"href": "/"
				},
				{
					"text": "Organic & Natural",
					"href": "/organic-and-natural/"
				},
				{
					"text": "Nature-Inspired Curves Style"
				}
			]
		},
		{
			"fu_type": "o_hero",
			"a_image": {
				"alt": "Nature-Inspired Curves style mood board — Organic · Fluid Forms",
				"width": "1024",
				"height": "768",
				"src": "/assets/imgs/organic-and-natural/nature-inspired-curves/lifestyle.jpg",
				"loading": "eager"
			},
			"a_eyebrow": "Organic · Fluid · Curved · Natural · Blob",
			"a_h1": "Nature-Inspired Curves Style",
			"a_description": "Flowing blob shapes, cloud-like containers, and the gentle organic curves of forms borrowed from water, wind, and growing things — Nature-Inspired Curves design dissolves the rigid geometry of traditional layouts into soft, undulating forms. The generous border-radius values, floating shadows, and sky-blue palette create interfaces that feel like they grew organically rather than being constructed on a grid.",
			"m_buttons": [
				{
					"text": "Colors",
					"href": "#color-palettes",
					"style": "primary"
				},
				{
					"text": "Fonts",
					"href": "#typography",
					"style": "secondary"
				}
			],
			"section_id": "nature-inspired-curves"
		},
		{
			"fu_type": "o_style_guide",
			"a_h2": "When to Use",
			"a_description": "This organically flowing style powers wellness apps, yoga studio websites, children's education platforms, and creative brainstorming tools. You'll see it on skincare brand sites, meditation app landing pages, natural cosmetics companies, and any interface that wants to feel approachable and soft — where the absence of sharp corners communicates warmth, safety, and natural harmony.",
			"copy_label": "Click to copy prompt",
			"copied_label": "Prompt copied!",
			"items": [
				{
					"a_image_cover": {
						"alt": "Nature-Inspired Curves style use case illustration",
						"width": "1024",
						"height": "768",
						"src": "/assets/imgs/organic-and-natural/nature-inspired-curves/use-cases.jpg",
						"loading": "lazy"
					},
					"a_icon": {"icon": "{lucide-icon}"},
					"a_h3": "{Industry/Use Case 1}",
					"a_description": "{Specific examples, comma-separated}"
				},
				{
					"a_image_cover": {
						"alt": "Nature-Inspired Curves style use case illustration",
						"width": "1024",
						"height": "768",
						"src": "/assets/imgs/organic-and-natural/nature-inspired-curves/use-cases.jpg",
						"loading": "lazy"
					},
					"a_icon": {"icon": "{lucide-icon}"},
					"a_h3": "{Industry/Use Case 2}",
					"a_description": "{Specific examples, comma-separated}"
				},
				{
					"a_image_cover": {
						"alt": "Nature-Inspired Curves style use case illustration",
						"width": "1024",
						"height": "768",
						"src": "/assets/imgs/organic-and-natural/nature-inspired-curves/use-cases.jpg",
						"loading": "lazy"
					},
					"a_icon": {"icon": "{lucide-icon}"},
					"a_h3": "{Industry/Use Case 3}",
					"a_description": "{Specific examples, comma-separated}"
				}
			]
		},
		{
			"fu_type": "o_design_images",
			"a_eyebrow": "Prompt",
			"a_h2": "Built From This",
			"a_description": "The soft, flowing aesthetic of nature-inspired curves — blob shapes, organic borders, and the gentle undulation of forms borrowed from water, clouds, and growing things. Background: soft sky blue (#f0f7ff). The .inner panel has a white background (#ffffff) with a large border-radius (24px) and a soft shadow (0 4px 20px rgba(0,0,0,0.05)) — a cloud-like form floating against the sky. Colors: ocean blue (#3b82f6) as the primary accent — the blue of water, the medium through which nature's curves flow most beautifully. Deep navy (#1e3a5f) for headings, soft blue-gray (#6b8caa) for body text. The aesthetic is soft and flowing — hard edges dissolved into curves, straight lines replaced by organic undulations. Set in Outfit — a modern sans-serif with gentle curves and balanced proportions. Heading at weight 600, 26px, line-height 1.3, color #1e3a5f. Eyebrow at weight 500, 11px, uppercase, 2px letter-spacing, color #3b82f6. Body at weight 400, 15px, line-height 1.7, color #6b8caa. Buttons: primary — ocean blue (#3b82f6), white text, 50px border-radius (pill). Secondary: transparent, blue border, pill shape. Alternatives: Nunito (rounded friendly), Comfortaa (display rounded).",
			"items": [
				{
					"a_image": {
						"alt": "Nature-Inspired Curves style UI example",
						"width": "800",
						"height": "600",
						"src": "https://placehold.co/800x600",
						"href": "/assets/gallery/organic-and-natural/nature-inspired-curves/example.html",
						"loading": "lazy"
					},
					"tags": [
						"{Tag 1}",
						"{Tag 2}",
						"{Tag 3}",
						"{Tag 4}"
					],
					"ignore": "1"
				},
				{
					"a_image": {
						"alt": "Nature-Inspired Curves style UI example",
						"width": "800",
						"height": "600",
						"src": "https://placehold.co/800x600",
						"href": "/assets/gallery/organic-and-natural/nature-inspired-curves/example.html",
						"loading": "lazy"
					},
					"tags": [
						"{Tag 1}",
						"{Tag 2}",
						"{Tag 3}",
						"{Tag 4}"
					],
					"ignore": "1"
				},
				{
					"a_image": {
						"alt": "Nature-Inspired Curves style UI example",
						"width": "800",
						"height": "600",
						"src": "https://placehold.co/800x600",
						"href": "/assets/gallery/organic-and-natural/nature-inspired-curves/example.html",
						"loading": "lazy"
					},
					"tags": [
						"{Tag 1}",
						"{Tag 2}",
						"{Tag 3}",
						"{Tag 4}"
					],
					"ignore": "1"
				},
				{
					"a_image": {
						"alt": "Nature-Inspired Curves style UI example",
						"width": "800",
						"height": "600",
						"src": "https://placehold.co/800x600",
						"href": "/assets/gallery/organic-and-natural/nature-inspired-curves/example.html",
						"loading": "lazy"
					},
					"tags": [
						"{Tag 1}",
						"{Tag 2}",
						"{Tag 3}",
						"{Tag 4}"
					],
					"ignore": "1"
				}
			]
		},
		{
			"fu_type": "o_style_guide",
			"a_h2": "Design Principles",
			"copy_label": "Click to copy prompt",
			"copied_label": "Prompt copied!",
			"items": [
				{
					"a_image_cover": {
						"alt": "Nature-Inspired Curves style design principle illustration",
						"width": "1024",
						"height": "768",
						"src": "/assets/imgs/organic-and-natural/nature-inspired-curves/principle.jpg",
						"loading": "lazy"
					},
					"a_icon": {"icon": "{lucide-icon}"},
					"a_h3": "{Principle 1 Name}",
					"a_description": "{2-3 sentences explaining this design principle.}"
				},
				{
					"a_image_cover": {
						"alt": "Nature-Inspired Curves style design principle illustration",
						"width": "1024",
						"height": "768",
						"src": "/assets/imgs/organic-and-natural/nature-inspired-curves/principle.jpg",
						"loading": "lazy"
					},
					"a_icon": {"icon": "{lucide-icon}"},
					"a_h3": "{Principle 2 Name}",
					"a_description": "{2-3 sentences explaining this design principle.}"
				},
				{
					"a_image_cover": {
						"alt": "Nature-Inspired Curves style design principle illustration",
						"width": "1024",
						"height": "768",
						"src": "/assets/imgs/organic-and-natural/nature-inspired-curves/principle.jpg",
						"loading": "lazy"
					},
					"a_icon": {"icon": "{lucide-icon}"},
					"a_h3": "{Principle 3 Name}",
					"a_description": "{2-3 sentences explaining this design principle.}"
				},
				{
					"a_image_cover": {
						"alt": "Nature-Inspired Curves style design principle illustration",
						"width": "1024",
						"height": "768",
						"src": "/assets/imgs/organic-and-natural/nature-inspired-curves/principle.jpg",
						"loading": "lazy"
					},
					"a_icon": {"icon": "{lucide-icon}"},
					"a_h3": "{Principle 4 Name}",
					"a_description": "{2-3 sentences explaining this design principle.}"
				},
				{
					"a_image_cover": {
						"alt": "Nature-Inspired Curves style design principle illustration",
						"width": "1024",
						"height": "768",
						"src": "/assets/imgs/organic-and-natural/nature-inspired-curves/principle.jpg",
						"loading": "lazy"
					},
					"a_icon": {"icon": "{lucide-icon}"},
					"a_h3": "{Principle 5 Name}",
					"a_description": "{2-3 sentences explaining this design principle.}"
				},
				{
					"a_image_cover": {
						"alt": "Nature-Inspired Curves style design principle illustration",
						"width": "1024",
						"height": "768",
						"src": "/assets/imgs/organic-and-natural/nature-inspired-curves/principle.jpg",
						"loading": "lazy"
					},
					"a_icon": {"icon": "{lucide-icon}"},
					"a_h3": "{Principle 6 Name}",
					"a_description": "{2-3 sentences explaining this design principle.}"
				}
			]
		},
		{
			"fu_type": "o_color_palette",
			"a_eyebrow": "Color Palette #1",
			"a_h2": "{Palette Name}",
			"a_description": "{What this palette represents — the core identity}",
			"copy_label": "Copy",
			"copied_label": "Copied!",
			"colors": [
				{
					"a_h3": "{Color Name}",
					"hex": "#000000",
					"a_description": "{Where to use: primary action, headlines, etc.}"
				},
				{
					"a_h3": "{Color Name}",
					"hex": "#000000",
					"a_description": "{Where to use}"
				},
				{
					"a_h3": "{Color Name}",
					"hex": "#000000",
					"a_description": "{Where to use}"
				},
				{
					"a_h3": "{Color Name}",
					"hex": "#000000",
					"a_description": "{Where to use}"
				},
				{
					"a_h3": "{Color Name}",
					"hex": "#FFFFFF",
					"a_description": "{Where to use}"
				},
				{
					"a_h3": "{Color Name}",
					"hex": "#888888",
					"a_description": "{Where to use}"
				}
			],
			"section_id": "color-palettes"
		},
		{
			"fu_type": "o_color_palette",
			"a_eyebrow": "Color Palette #2",
			"a_h2": "{Palette 2 Name}",
			"a_description": "{How this differs from palette #1 — darker, lighter, more saturated, etc.}",
			"copy_label": "Copy",
			"copied_label": "Copied!",
			"colors": [
				{
					"a_h3": "{Color Name}",
					"hex": "#000000",
					"a_description": "{Where to use}"
				},
				{
					"a_h3": "{Color Name}",
					"hex": "#000000",
					"a_description": "{Where to use}"
				},
				{
					"a_h3": "{Color Name}",
					"hex": "#000000",
					"a_description": "{Where to use}"
				},
				{
					"a_h3": "{Color Name}",
					"hex": "#000000",
					"a_description": "{Where to use}"
				},
				{
					"a_h3": "{Color Name}",
					"hex": "#FFFFFF",
					"a_description": "{Where to use}"
				}
			],
			"section_id": "{palette-2-slug}"
		},
		{
			"fu_type": "o_color_palette",
			"a_eyebrow": "Color Palette #3",
			"a_h2": "{Palette 3 Name}",
			"a_description": "{How this differs — bolder, experimental, etc.}",
			"copy_label": "Copy",
			"copied_label": "Copied!",
			"colors": [
				{
					"a_h3": "{Color Name}",
					"hex": "#000000",
					"a_description": "{Where to use}"
				},
				{
					"a_h3": "{Color Name}",
					"hex": "#000000",
					"a_description": "{Where to use}"
				},
				{
					"a_h3": "{Color Name}",
					"hex": "#000000",
					"a_description": "{Where to use}"
				},
				{
					"a_h3": "{Color Name}",
					"hex": "#000000",
					"a_description": "{Where to use}"
				},
				{
					"a_h3": "{Color Name}",
					"hex": "#FFFFFF",
					"a_description": "{Where to use}"
				}
			],
			"section_id": "{palette-3-slug}"
		},
		{
			"fu_type": "o_typography",
			"a_eyebrow": "Typography",
			"a_h2": "Heading Fonts",
			"a_description": "{What kind of typefaces define this style's headlines.}",
			"copy_label": "Copy",
			"copied_label": "Copied!",
			"fonts": [
				{
					"fu_type": "font",
					"a_eyebrow": "Google",
					"family": "{Font Name}",
					"css": "font-family: '{Font Name}', serif; font-weight: 700; font-size: 1.5rem; line-height: 1.15;"
				},
				{
					"fu_type": "font",
					"a_eyebrow": "Google",
					"family": "{Font Name}",
					"css": "font-family: '{Font Name}', serif; font-weight: 700; font-size: 1.5rem; line-height: 1.15;"
				},
				{
					"fu_type": "font",
					"a_eyebrow": "Google",
					"family": "{Font Name}",
					"css": "font-family: '{Font Name}', serif; font-weight: 700; font-size: 1.5rem; line-height: 1.15;"
				},
				{
					"fu_type": "font",
					"a_eyebrow": "Google",
					"family": "{Font Name}",
					"css": "font-family: '{Font Name}', serif; font-weight: 700; font-size: 1.5rem; line-height: 1.15;"
				},
				{
					"fu_type": "font",
					"a_eyebrow": "Google",
					"family": "{Font Name}",
					"css": "font-family: '{Font Name}', serif; font-weight: 700; font-size: 1.5rem; line-height: 1.15;"
				},
				{
					"fu_type": "font",
					"a_eyebrow": "System",
					"family": "{Font Name}",
					"css": "font-family: {Font Name}, serif; font-weight: 700; font-size: 1.5rem; line-height: 1.15;"
				},
				{
					"fu_type": "font",
					"a_eyebrow": "System",
					"family": "{Font Name}",
					"css": "font-family: {Font Name}, serif; font-weight: 700; font-size: 1.5rem; line-height: 1.2;"
				},
				{
					"fu_type": "font",
					"a_eyebrow": "System",
					"family": "{Font Name}",
					"css": "font-family: {Font Name}, serif; font-weight: 700; font-size: 1.5rem; line-height: 1.2;"
				}
			],
			"section_id": "typography"
		},
		{
			"fu_type": "o_typography",
			"a_eyebrow": "Typography",
			"a_h2": "Text Fonts",
			"a_description": "{What kind of typefaces work for body copy in this style.}",
			"copy_label": "Copy",
			"copied_label": "Copied!",
			"fonts": [
				{
					"fu_type": "font",
					"a_eyebrow": "Google",
					"family": "{Font Name}",
					"css": "font-family: '{Font Name}', sans-serif; font-weight: 400; font-size: 1rem; line-height: 1.6;"
				},
				{
					"fu_type": "font",
					"a_eyebrow": "Google",
					"family": "{Font Name}",
					"css": "font-family: '{Font Name}', serif; font-weight: 400; font-size: 1rem; line-height: 1.7;"
				},
				{
					"fu_type": "font",
					"a_eyebrow": "System",
					"family": "{Font Name}",
					"css": "font-family: {Font Name}, sans-serif; font-weight: 400; font-size: 1rem; line-height: 1.6;"
				},
				{
					"fu_type": "font",
					"a_eyebrow": "System",
					"family": "{Font Name}",
					"css": "font-family: {Font Name}, sans-serif; font-weight: 400; font-size: 1rem; line-height: 1.6;"
				},
				{
					"fu_type": "font",
					"a_eyebrow": "System",
					"family": "{Font Name}",
					"css": "font-family: {Font Name}, serif; font-weight: 400; font-size: 1rem; line-height: 1.7;"
				}
			]
		},
		{
			"fu_type": "o_style_guide",
			"a_h2": "History",
			"copy_label": "Click to copy prompt",
			"copied_label": "Prompt copied!",
			"items": [
				{
					"a_image_cover": {
						"alt": "Nature-Inspired Curves style history illustration",
						"width": "1024",
						"height": "768",
						"src": "/assets/imgs/organic-and-natural/nature-inspired-curves/history.jpg",
						"loading": "lazy"
					},
					"a_h3": "{Origins — what era/movement it came from}",
					"a_description": "{Paragraph about the cultural context and emergence of this style.}"
				},
				{
					"a_image_cover": {
						"alt": "Nature-Inspired Curves style history illustration",
						"width": "1024",
						"height": "768",
						"src": "/assets/imgs/organic-and-natural/nature-inspired-curves/history.jpg",
						"loading": "lazy"
					},
					"a_h3": "{Peak — the defining medium or movement}",
					"a_description": "{Paragraph about the style's golden age — who shaped it, where it appeared, what made it iconic.}"
				},
				{
					"a_image_cover": {
						"alt": "Nature-Inspired Curves style history illustration",
						"width": "1024",
						"height": "768",
						"src": "/assets/imgs/organic-and-natural/nature-inspired-curves/history.jpg",
						"loading": "lazy"
					},
					"a_h3": "{Modern Revival or Legacy}",
					"a_description": "{Paragraph about how this style is used today — what brands, industries, or movements have adopted it.}"
				}
			]
		},
		{
			"fu_type": "o_faq",
			"a_h2": "FAQ",
			"a_description": "Common questions about Nature-Inspired Curves style, color palettes, and usage.",
			"items": [
				{
					"a_icon": {"icon": "bot"},
					"a_h3": "What AI prompt generates a Nature-Inspired Curves website?",
					"answer": "The soft, flowing aesthetic of nature-inspired curves — blob shapes, organic borders, and the gentle undulation of forms borrowed from water, clouds, and growing things. Background: soft sky blue (#f0f7ff). The .inner panel has a white background (#ffffff) with a large border-radius (24px) and a soft shadow (0 4px 20px rgba(0,0,0,0.05)) — a cloud-like form floating against the sky. Colors: ocean blue (#3b82f6) as the primary accent — the blue of water, the medium through which nature's curves flow most beautifully. Deep navy (#1e3a5f) for headings, soft blue-gray (#6b8caa) for body text. The aesthetic is soft and flowing — hard edges dissolved into curves, straight lines replaced by organic undulations. Set in Outfit — a modern sans-serif with gentle curves and balanced proportions. Heading at weight 600, 26px, line-height 1.3, color #1e3a5f. Eyebrow at weight 500, 11px, uppercase, 2px letter-spacing, color #3b82f6. Body at weight 400, 15px, line-height 1.7, color #6b8caa. Buttons: primary — ocean blue (#3b82f6), white text, 50px border-radius (pill). Secondary: transparent, blue border, pill shape. Alternatives: Nunito (rounded friendly), Comfortaa (display rounded)."
				},
				{
					"a_icon": {"icon": "briefcase"},
					"a_h3": "What industries does Nature-Inspired Curves work best for?",
					"answer": "{Detailed answer about ideal industries and contexts, plus what it doesn't work for.}"
				},
				{
					"a_icon": {"icon": "swatch-book"},
					"a_h3": "Which color palette should I choose?",
					"answer": "{Brief description of each palette and when to use it.}"
				},
				{
					"a_icon": {"icon": "circle-slash"},
					"a_h3": "When should I avoid using the Nature-Inspired Curves style?",
					"answer": "{Contexts where this style is a poor fit.}"
				},
				{
					"a_icon": {"icon": "{lucide-icon}"},
					"a_h3": "{Historical or cultural question about this style}",
					"answer": "{Answer with cultural/historical context.}"
				},
				{
					"a_icon": {"icon": "type"},
					"a_h3": "What fonts best capture the Nature-Inspired Curves look?",
					"answer": "{Detailed typography recommendations with reasoning.}"
				}
			],
			"section_id": "faq"
		},
		{
			"fu_type": "o_design_images",
			"a_h2": "Similar Designs",
			"items": [
				{
					"a_image": {
						"alt": "Biophilic Design style preview",
						"width": "800",
						"height": "600",
						"src": "/assets/styles/organic-and-natural/biophilic-design.jpg",
						"href": "/organic-and-natural/biophilic-design/",
						"loading": "lazy"
					},
					"tags": [
						"Organic",
						"Natural",
						"Illustrated"
					]
				},
				{
					"a_image": {
						"alt": "Botanical Theme style preview",
						"width": "800",
						"height": "600",
						"src": "/assets/styles/organic-and-natural/botanical-theme.jpg",
						"href": "/organic-and-natural/botanical-theme/",
						"loading": "lazy"
					},
					"tags": [
						"Organic",
						"Natural",
						"Earthy"
					]
				},
				{
					"a_image": {
						"alt": "Earthy Palette style preview",
						"width": "800",
						"height": "600",
						"src": "/assets/styles/organic-and-natural/earthy-palette.jpg",
						"href": "/organic-and-natural/earthy-palette/",
						"loading": "lazy"
					},
					"tags": [
						"Organic",
						"Earthy",
						"Earth Tones"
					]
				},
				{
					"a_image": {
						"alt": "Eco Branding style preview",
						"width": "800",
						"height": "600",
						"src": "/assets/styles/organic-and-natural/eco-branding.jpg",
						"href": "/organic-and-natural/eco-branding/",
						"loading": "lazy"
					},
					"tags": [
						"Organic",
						"Natural",
						"Earthy"
					]
				}
			]
		}
	],
	"seo": {
		"title": "Nature-Inspired Curves Style — UI Lookbook",
		"description": "Explore the Nature-Inspired Curves style: Organic · Fluid Forms. Color palettes, typography, design principles, and AI prompts for Nature-Inspired Curves UI design.",
		"keywords": "Nature-Inspired Curves, nature-inspired-curves, Organic, Fluid, Curved, Natural, Blob",
		"og": {
			"title": "Nature-Inspired Curves Style — UI Lookbook",
			"description": "Explore the Nature-Inspired Curves style: Organic · Fluid Forms. Color palettes, typography, design principles, and AI prompts.",
			"url": "https://uilookbook.com/organic-and-natural/nature-inspired-curves/",
			"type": "article",
			"image": {
				"src": "/assets/imgs/organic-and-natural/nature-inspired-curves/lifestyle.jpg",
				"alt": "Nature-Inspired Curves Style — UI Lookbook"
			}
		},
		"twitter": {
			"card": "summary_large_image",
			"title": "Nature-Inspired Curves Style — UI Lookbook",
			"description": "Explore the Nature-Inspired Curves style: Organic · Fluid Forms. Color palettes, typography, design principles, and AI prompts.",
			"image": {
				"src": "/assets/imgs/organic-and-natural/nature-inspired-curves/lifestyle.jpg",
				"alt": "Nature-Inspired Curves Style — UI Lookbook"
			}
		}
	},
	"settings": {
		"start_head_codes": [],
		"head_codes": [
			{
				"note": "Google Fonts",
				"code": "<link rel=\"stylesheet\" href=\"https://fonts.googleapis.com/css2?family=Outfit:wght@300;400;500;600;700&display=swap\">"
			},
			{
				"note": "nature-inspired-curves",
				"code": "<link rel=\"stylesheet\" href=\"/assets/styles/organic-and-natural/nature-inspired-curves.css\">"
			}
		],
		"start_body_codes": [],
		"body_codes": [],
		"alternate": []
	}
}
